gravitybee/__init__.py
gravitybee/cli.py
gravitybee/distutils_utils.py
gravitybee/hook-template
gravitybee/logging.conf
gravitybee-0.4.6.dist-info/LICENSE
gravitybee-0.4.6.dist-info/METADATA
gravitybee-0.4.6.dist-info/WHEEL
gravitybee-0.4.6.dist-info/entry_points.txt
gravitybee-0.4.6.dist-info/top_level.txt
gravitybee-0.4.6.dist-info/RECORD
