Metadata-Version: 2.1
Name: gravitybee
Version: 0.4.6
Summary: Generate standalone python applications.
Home-page: https://github.com/plus3it/gravitybee
Author: YakDriver
Author-email: projects@plus3it.com
License: Apache Software License 2.0
Platform: Linux
Platform: Windows
Platform: Darwin
Classifier: Development Status :: 4 - Beta
Classifier: Intended Audience :: Developers
Classifier: License :: OSI Approved :: Apache Software License
Classifier: Operating System :: MacOS :: MacOS X
Classifier: Operating System :: POSIX :: Linux
Classifier: Operating System :: Microsoft :: Windows
Classifier: Programming Language :: Python
Classifier: Programming Language :: Python :: 3
Classifier: Programming Language :: Python :: 3.7
Classifier: Programming Language :: Python :: 3.8
Classifier: Programming Language :: Python :: 3.9
Classifier: Programming Language :: Python :: 3.10
Classifier: Programming Language :: Python :: Implementation :: CPython
Classifier: Programming Language :: Python :: Implementation :: PyPy
Classifier: Topic :: Utilities
License-File: LICENSE
Requires-Dist: click
Requires-Dist: PyInstaller
Requires-Dist: pyppyn (>=0.4.6)
